rasim_project/__init__.py
rasim_project-0.1.0.dist-info/METADATA
rasim_project-0.1.0.dist-info/WHEEL
rasim_project-0.1.0.dist-info/top_level.txt
rasim_project-0.1.0.dist-info/RECORD
