Metadata-Version: 2.1
Name: rasim_project
Version: 0.1.0
Summary: A short description of the package
Author: Your Name
Author-email: your-email@example.com
